revolving_asyncio/__init__.py
revolving_asyncio/_version.py
revolving_asyncio-0.1.2.dist-info/METADATA
revolving_asyncio-0.1.2.dist-info/WHEEL
revolving_asyncio-0.1.2.dist-info/licenses/LICENSE
revolving_asyncio-0.1.2.dist-info/RECORD
