Metadata-Version: 2.4
Name: revolving_asyncio
Version: 0.1.2
Summary: easy to covert between sync and async
Author-email: wukan <wu-kan@163.com>
License: MIT
License-File: LICENSE
Keywords: async,asyncio,sync
Classifier: Development Status :: 4 - Beta
Classifier: Programming Language :: Python
Requires-Python: >=3.6
Requires-Dist: nest-asyncio
